MockLogging.py
__init__.py
pWebServer.py
pwebserver-25.8a6.dist-info/METADATA
pwebserver-25.8a6.dist-info/WHEEL
pwebserver-25.8a6.dist-info/entry_points.txt
pwebserver-25.8a6.dist-info/licenses/LICENSE
pwebserver-25.8a6.dist-info/RECORD
