Metadata-Version: 2.1
Name: pWebServer
Version: 25.8a6
Summary: Small, asynchronous web server for use with Raspberry Pi Pico W boards and similar
Author-Email: Stephen Sadowski <stephen.sadowski+opensource@sjsadowski.com>
License: MIT
Requires-Python: >=3.11
